duron/__init__.py
duron/_core/__init__.py
duron/_core/config.py
duron/_core/context.py
duron/_core/ops.py
duron/_core/session.py
duron/_core/signal.py
duron/_core/stream.py
duron/_core/stream_manager.py
duron/_core/task_manager.py
duron/_core/utils.py
duron/_decorator/__init__.py
duron/_decorator/durable.py
duron/_decorator/effect.py
duron/codec/__init__.py
duron/codec/_base.py
duron/contrib/__init__.py
duron/contrib/codecs.py
duron/contrib/storage.py
duron/log/__init__.py
duron/log/_entry.py
duron/log/_helper.py
duron/log/_storage.py
duron/loop.py
duron/py.typed
duron/tracing/__init__.py
duron/tracing/_events.py
duron/tracing/_span.py
duron/tracing/_tracer.py
duron/typing/__init__.py
duron/typing/_hint.py
duron/typing/_inspect.py
duron-0.0.2.dist-info/WHEEL
duron-0.0.2.dist-info/METADATA
duron-0.0.2.dist-info/RECORD
