Metadata-Version: 2.4
Name: duron
Version: 0.0.2
Summary: Durable async runtime for Python
License-Expression: Apache-2.0
Classifier: Development Status :: 3 - Alpha
Classifier: License :: OSI Approved :: Apache Software License
Classifier: Topic :: Software Development :: Libraries
Classifier: Intended Audience :: Developers
Classifier: Framework :: AsyncIO
Classifier: Operating System :: OS Independent
Classifier: Programming Language :: Python :: 3 :: Only
Classifier: Programming Language :: Python :: 3.10
Classifier: Programming Language :: Python :: 3.11
Classifier: Programming Language :: Python :: 3.12
Classifier: Programming Language :: Python :: 3.13
Classifier: Programming Language :: Python :: 3.14
Requires-Dist: typing-extensions>=4.15.0
Requires-Python: >=3.10
Project-URL: Homepage, https://brian14708.github.io/duron/
Project-URL: Source, https://github.com/brian14708/duron
